ui_zero/__init__.py
ui_zero/adb.py
ui_zero/agent.py
ui_zero/cli.py
ui_zero/env_config.py
ui_zero/localization.py
ui_zero/logging_config.py
ui_zero/server.py
ui_zero/ui_display.py
ui_zero/locale/messages.pot
ui_zero/locale/en_US/LC_MESSAGES/ui_zero.mo
ui_zero/locale/en_US/LC_MESSAGES/ui_zero.po
ui_zero/locale/zh_CN/LC_MESSAGES/ui_zero.mo
ui_zero/locale/zh_CN/LC_MESSAGES/ui_zero.po
ui_zero/models/__init__.py
ui_zero/models/arkmodel.py
ui_zero/models/doubao_ui_tars.py
ui_zero-0.1.11.dist-info/METADATA
ui_zero-0.1.11.dist-info/WHEEL
ui_zero-0.1.11.dist-info/entry_points.txt
ui_zero-0.1.11.dist-info/licenses/LICENSE
ui_zero-0.1.11.dist-info/RECORD
