Metadata-Version: 2.4
Name: ui-zero
Version: 0.1.11
Summary: AI-powered UI automation testing library
Project-URL: Homepage, https://github.com/Roland0511/ui-zero
Project-URL: Documentation, https://github.com/Roland0511/ui-zero#readme
Project-URL: Repository, https://github.com/Roland0511/ui-zero.git
Project-URL: Issues, https://github.com/Roland0511/ui-zero/issues
Author-email: "lizhou.zhu" <rolandlivingstone@gmail.com>
License: MIT License
License-File: LICENSE
Keywords: adb,ai,android,automation,testing,ui
Classifier: Development Status :: 3 - Alpha
Classifier: Intended Audience :: Developers
Classifier: License :: OSI Approved :: MIT License
Classifier: Operating System :: OS Independent
Classifier: Programming Language :: Python :: 3
Classifier: Programming Language :: Python :: 3.10
Classifier: Programming Language :: Python :: 3.11
Classifier: Programming Language :: Python :: 3.12
Classifier: Topic :: Software Development :: Libraries :: Python Modules
Classifier: Topic :: Software Development :: Testing
Requires-Python: >=3.10
Requires-Dist: fastapi>=0.104.0
Requires-Dist: ffmpeg-python>=0.2.0
Requires-Dist: matplotlib>=3.10.1
Requires-Dist: openai>=1.86.0
Requires-Dist: pillow>=11.2.1
Requires-Dist: python-dotenv>=1.1.0
Requires-Dist: pyyaml>=6.0.0
Requires-Dist: rich>=13.0.0
Requires-Dist: uvicorn>=0.24.0
Requires-Dist: websockets>=12.0
